{
  "cli": {
    "version": ">= 12.0.0",
    "appVersionSource": "local"
  },
  "build": {
    "rider-staging": {
      "distribution": "internal",
      "channel": "rider-staging",
      "android": {
        "buildType": "apk"
      },
      "env": {
        "APP_VARIANT": "staging",
        "EXPO_PUBLIC_API_BASE_URL": "https://karigo-8htn.onrender.com/api/v1"
      }
    },
    "rider-staging-ios-simulator": {
      "distribution": "internal",
      "channel": "rider-staging",
      "ios": {
        "simulator": true
      },
      "env": {
        "APP_VARIANT": "staging",
        "EXPO_PUBLIC_API_BASE_URL": "https://karigo-8htn.onrender.com/api/v1"
      }
    },
    "captain-production": {
      "distribution": "store",
      "channel": "captain-production",
      "android": {
        "buildType": "app-bundle"
      },
      "env": {
        "APP_VARIANT": "production",
        "EXPO_PUBLIC_API_BASE_URL": "https://karigo-8htn.onrender.com/api/v1"
      }
    }
  },
  "submit": {}
}
